{
  "url": "https://www.tosspayments.com/blog/articles/semo-85",
  "title": "스마트스토어 상위노출 시키는 키워드 분석 팁 총정리",
  "content_ordered": [
    {
      "type": "text",
      "data": "[사장님백서] 경쟁력 있는 키워드를 찾고 검색 노출에 최적화하는 방법을 알려드려요."
    },
    {
      "type": "text",
      "data": "10분만 시간 내면"
    },
    {
      "type": "text",
      "data": "✔️ 스마트스토어 키워드의 의미와 종류에 대해 알 수 있어요.\n✔️ 스마트스토어 키워드 분석에 유용한 사이트를 알 수 있어요.\n✔️ 스마트스토어 상품 등록할 때 키워드 최적화하는 방법을 알 수 있어요."
    },
    {
      "type": "text",
      "data": "스마트스토어, 키워드가 전부다?"
    },
    {
      "type": "text",
      "data": "스마트스토어를 운영 중인 사장님이라면 ‘키워드’에 대해 들어보셨을 거예요. 판매 상품을 더 많이 노출시키기 위해 많은 사장님이 키워드 광고 상품을 이용하기도 하는데요. 하지만 경쟁력이 없는 광고 키워드를 사용할 경우 아무리 광고비를 많이 써도 효과가 미미할 수 있어요."
    },
    {
      "type": "text",
      "data": "어떻게 해야 좋은 키워드를 찾아 매출을 높일 수 있을지 궁금하다면 이 글을 확인해 보세요. 키워드 발굴 팁부터 지금 사용 중인 키워드 효율을 점검해 볼 수 있는 방법까지 알려드릴게요."
    },
    {
      "type": "text",
      "data": "스마트스토어 ‘키워드’가 뭔가요?"
    },
    {
      "type": "text",
      "data": "스마트스토어 매출을 높이기 위해서는 키워드에 대해 잘 알아야 해요. 스마트스토어와 키워드는 뗄 수 없는 관계인데요. 상위노출을 위해 활용할 수 있는 전략 대부분이 키워드와 관련이 있어요."
    },
    {
      "type": "text",
      "data": "📌 키워드란?"
    },
    {
      "type": "text",
      "data": "검색 과정에서 상품이 노출될 수 있도록 만드는 단어를 의미해요. ‘검색어’와 비슷하다고 볼 수 있어요. 고객이 특정 단어를 검색할 때 사장님 상품이 페이지 상단에 노출된다면 구매로 이어질 확률이 높아지죠. 이처럼 상위노출을 만들어주는 검색어를 좋은 키워드라고 해요."
    },
    {
      "type": "image",
      "img_url": "https://core-cdn-fe.toss.im/image/optimize/?src=https://static.toss.im/ipd-tcs/toss_core/live/61375a9b-81d4-4340-8d6f-c24cef79bc02/semo-85-inner-1-1-1536x761.jpg?&w=3840&q=75",
      "ocr_text": "햅 쇼 핑 | 290g = 카 테 고 리 더 보 기 쇼 핑 865 ㅜ ㅠ | 몰 전 체 보 기 A 쇼 핑 ~\n\n쇼 핑 인 관 | 겨 울 앙 고 라 양 말 시 나 모 롤 양 말 삭 스 타 즈 여 름 양 말 … 크 리 스 마 스 양 말 … 중 / 장 목 양 말 . 유 니 클 로 양 말 검 정 양 말 _ 유 니 클 로 히 트 텍 양 말 보 기 ㅜ\n\n“AS 양 말 ' 에 대 한 검 색 결 과 입 니 다\n\n국 산 따 뜻 한 통 파 일 무 지 FAL 쿠 션 기 모 AS 양 말\n2,250 원 © 2.500%\n\n패 션 잡 화 > 양 말 > 여 성 양 말 > 중 목 / 장 목 양 말\n\n사 용 계 절 : 봄 , 여 름 , 가 을 , 겨 울 _ 성 별 : 여 성 용\n\n리 뷰 6.585 ㆍ 구 매 건 수 16,066 ㆍ 등 록 일 2020.12. ㆍ <2 찜 하 기 1962 ㆍ O 신 고 하 기 Oss\n\n출 처 : 네 이 버 쇼 핑"
    },
    {
      "type": "text",
      "data": "스마트스토어 키워드는 기본적으로 상품명, 태그 등에 활용 가능해요. 더 상단에 상품을 노출하고 싶다면 키워드 광고를 이용해 볼 수도 있고요. 네이버 키워드 광고 세팅 방법이 궁금한 사장님은 <"
    },
    {
      "type": "text",
      "data": ">을 확인해 보세요."
    },
    {
      "type": "text",
      "data": "다양한 검색어를 거쳐 상품을 노출시키기 위해 상품명에는 ‘복합 키워드’를 사용하는 경우가 많은데요. 어떤 키워드를 통해 사장님 상품이 노출될 때 고객의 구매 의사가 더 높아질지 고민하는 과정을 거쳐야 효율이 좋은 키워드를 찾아낼 수 있어요."
    },
    {
      "type": "text",
      "data": "Q. 단일 키워드와 복합 키워드의 차이점은 무엇인가요?"
    },
    {
      "type": "text",
      "data": "단일 키워드는 ‘양말’, ‘담요’처럼 한 개의 단어로 이루어진 검색어를 의미해요. 복합 키워드는 두 개 이상의 단어로 이루어지는데요. ‘여성양말’, ‘겨울 양말’과 같이 상품의 세부적인 특징을 담고 있는 경우가 많아요."
    },
    {
      "type": "text",
      "data": "좋은 키워드, 어떻게 찾을 수 있나요?"
    },
    {
      "type": "text",
      "data": "사장님이 쇼핑몰에서 양말을 팔고 있다고 가정해 볼게요. ‘양말’, ‘겨울 잡화’과 같이 범용적인 키워드는 많은 판매자가 활용하기 때문에 경쟁이 심해 상위노출이 어려워요. 경쟁이 약한 키워드라도, 검색량 자체가 저조하다면 구매까지 이뤄지기 힘들죠."
    },
    {
      "type": "text",
      "data": "그렇기 때문에 꾸준한 분석과 시도를 통해 최적 키워드를 찾아야 해요."
    },
    {
      "type": "image",
      "img_url": "https://core-cdn-fe.toss.im/image/optimize/?src=https://static.toss.im/ipd-tcs/toss_core/live/e6dca5a1-573b-4977-9172-ca7ccc263399/semo-85-inner-2-2-1536x476.jpg?&w=3840&q=75",
      "ocr_text": ""
    },
    {
      "type": "text",
      "data": "키워드를 분석할 때 기본적으로 고려해야 할 사항은"
    },
    {
      "type": "text",
      "data": "‘검색 빈도’"
    },
    {
      "type": "text",
      "data": "와"
    },
    {
      "type": "text",
      "data": "‘관련 상품 수’"
    },
    {
      "type": "text",
      "data": "인데요. 소비자의 검색량은 많지만 관련 상품을 판매하는 곳이 적을수록 좋은 키워드겠죠. 추가로 포털"
    },
    {
      "type": "text",
      "data": "검색 시 최상단에 ‘쇼핑 영역’이 노출되는 쇼핑성 키워드"
    },
    {
      "type": "text",
      "data": "를 활용하는 게 효과적이에요."
    },
    {
      "type": "text",
      "data": "해당 항목들을 체크할 때 유용한 사이트들을 소개할게요. 기능을 체크해 보며 이용이 편리한 곳을 찾아보세요. 이외에도"
    },
    {
      "type": "text",
      "data": "네이버 통합검색 및 쇼핑, 유튜브의 자동완성 또는 연관 검색어 기능을 통해 관련 키워드를 추출해 볼 수 있어요"
    },
    {
      "type": "text",
      "data": ". 한 곳에서만 키워드를 찾는 것보다 여러 사이트를 함께 활용하는 것을 추천해요."
    },
    {
      "type": "text",
      "data": "✅"
    },
    {
      "type": "text",
      "data": "상품 카테고리별 인기검색어를 확인할 수 있는 사이트에요."
    },
    {
      "type": "text",
      "data": "[쇼핑인사이트] 탭에서 조회하고 싶은 분야와 기간을 선택하면 해당 시기 많은 사람들이 검색한 키워드가 무엇인지 알 수 있어요. 검색 매체나 연령대별 인기검색어도 함께 확인 가능해요."
    },
    {
      "type": "image",
      "img_url": "https://core-cdn-fe.toss.im/image/optimize/?src=https://static.toss.im/ipd-tcs/toss_core/live/14435ca4-ffe8-43bd-8b0d-3abfca428727/semo-85-inner-3-1-1-1536x1298.jpg?&w=3840&q=75",
      "ocr_text": "분 야 패 션 잡 화 < | > | 양 말 4 분 류\n\n기 간 일 간 * 1 개 월 3 개 월 1 년 . 직 접 입 력 20203 v || 01 v\n\n기 기 별 [ ] 전 체 LC) ec [ | sure ae\n\nQ 조 회 하 기\n\naa C1 [ ㅣ 2대 [ ㅣ 3 때 [\n\n02 * | ㆍ 2017 년 # 앨 부 터 조 회 할 수 있 습 니 다\n\naoc [ ㅣ 5 째 [ | 6 때 이상\n\n이 2022.10.02. ~ 2023.01.02. * 조 회 결 과 다 운 로 드\n\n케\n\n1\n\n12 일\n10 월\n\n22a\n108\n\n112\n128\n\naid 31 일\n\n02 일\n10 월 12 월\n\n10\n\nTOP 500\n\n여 성 양 말 인 기 검 색 어\n\n2022.10.02. ~ 2023.01.02.\n\n2/25 | < | >\n양 말\n\n페 이 크 삭스\n\n여 자 양 말\n여 성 양 말\n수 면 양 말\n겨 울 양 말\n\n여 자 발 목 양 말\n발 열 양 말\n\n임 산 부 수 면 양 말\n크 리 스 마 스 양 말\n덧 신\n\n출 처 : 네 이버 데 이 터 랩"
    },
    {
      "type": "text",
      "data": "이외에도 [검색어트렌드] 탭에서 그래프를 통해 연관키워드 간 검색 비중 차이를 보여주는 기능도 제공해요. 원하는 기간, 연령, 성별 등에 대해 필터링을 거친 결과도 확인할 수 있어요."
    },
    {
      "type": "text",
      "data": "상품 광고를 할 때 활용하면 좋은 사이트에요. 아직 광고를 집행하지 않더라도 회원 가입만 하면 무료로 사용 가능해요."
    },
    {
      "type": "text",
      "data": "광고시스템 내 [도구 > 키워드 도구] 탭에서 조회하고 싶은 키워드를 입력하면 연관키워드와 검색 및 클릭수, 경쟁정도 등을 알려줘요."
    },
    {
      "type": "image",
      "img_url": "https://core-cdn-fe.toss.im/image/optimize/?src=https://static.toss.im/ipd-tcs/toss_core/live/447fcc9d-b251-4796-9203-f7d5ab4deb5a/semo-85-inner-4-1536x983.jpg?&w=3840&q=75",
      "ocr_text": "키 워 드 도 구 ' 파 워 링 크 캠 페 인 ' 의 새 로 운 키 워 드 를 발 굴 해 보 세 요 . 도 움 말 보 기\n\n연 관 키 워 드 조 회 AS 원 하 는 기 준 으 로 MAPA 캠 페 인 의 연 관 키 워 드 를 조 회 하 세 요 .( 다 중 선 택 가 능 ) 99 임 력 값 지 우기 | ㅅ |\n\n떤 pel i ㅁ MAE | 체 크 후 선 택 하 세 요 [ 시 즌 월 체 크 후 선 택 하 세 요 ~\n\ni\n\n[\nmae i 2 . [\n1 | i Ow 체 크 후 선 택 하 세 요 | [ AS 테 마 | 체 크 후 선 택 하 세 요 기\n\n연 관 키 워 드 조 회 결 과 (1000 개 )\n\nee A dd]\n\n680000 희 ddd)\n\n출 처 : 네 이버 광 고"
    },
    {
      "type": "text",
      "data": "조회 결과 페이지에서 원하는 키워드를 선택해 키워드 입찰가와 그에 따른 예상 성과도 확인해 볼 수 있는데요. 이를 바탕으로 어느 정도의 비용으로 키워드 광고를 입찰해야 목표 판매량에 도달 가능한지 가늠한 후 광고를 시작해 보세요."
    },
    {
      "type": "text",
      "data": "스마트스토어를 운영하는 많은 사장님들이 이용하는 사이트인데요."
    },
    {
      "type": "text",
      "data": "키워드 검색수, 경쟁률뿐만 아니라 상위 노출을 위한 상품 카테고리와 추천 상품명까지 알 수 있어요."
    },
    {
      "type": "image",
      "img_url": "https://core-cdn-fe.toss.im/image/optimize/?src=https://static.toss.im/ipd-tcs/toss_core/live/d38bb6ea-1559-46bd-bd12-d0318e0593a3/semo-85-inner-5-1536x1013.jpg?&w=3840&q=75",
      "ocr_text": "ry\n\nL\n\n양 말 선 물 세 트\n\n개 요 상 품 목 록\n\na\nLa\n네 이버 네 이버 쇼 핑 쿠 팡 1688 Alibaba\n\n4 패 션 잡 화 et 여 성 양 말 SRR (100%)\nain\nANY\n\n상 품 수 186.983 기 70040 。 6 개 월 매 솔 22150 만 원\n한 달 검 색 수 7.480 ®|\neae 70080 。 6 개 월 매 출 24,284 만 원\n경 쟁 강 도 실 거 래 상 품 비 율 _ 、 묶 음 상 품 비 율\n25.008 88% 0m 40%\n상 품 종 합 지 표\n\n상 품 수 186.983 개\n> 검 색 수 7480 회\n\n연 관 키 워 드\n\nTaoBao\n\n< 개 월 판 매량 . 63,0329 평 균 가 격\n\n67 EHH . 66,998 개 、 평 균 가 격\n\n해 외 상 품 비 율 1 년 내 게 시 비 율\n0% 대 70%\n\n1 개 월 13%, 6 개 월 48%\n\n8,600 2\n\n8,100 2\n\n검 색 최 적 화\n\n연 관 키 워 드\n\n키 워 드 검 색 수 상 품 수\n양 말 도 매 3.260 43818\n예 쁜 양 말 5210 9,593,431\n수 면 양 말 선 물 세 트 100 11.941\n두 발 루 양 말 1710 950\n폴 로 양 말 12270 55,799\n명 품 양 말 7,930 41548\n\n출 처 : 아 이템 스 카 우 트"
    },
    {
      "type": "text",
      "data": "이외에도 해당 사이트에서는 [연관 키워드] 탭에서 네이버 외 다른 포털 사이트와 오픈마켓에서의 사이트별 관련 키워드를 제공하고 있어요."
    },
    {
      "type": "text",
      "data": "스마트스토어와 함께 다른 판매처를 운영 중이라면 이 사이트에서 데이터를 확인해 보기를 추천해요."
    },
    {
      "type": "text",
      "data": "키워드 분석과 더불어 상품 평균 가격, 연관키워드 등을 한 번에 조회할 수 있어요."
    },
    {
      "type": "text",
      "data": "이와 함께 특정 키워드를 검색했을 때 상단에 뜨는 상품들이 지출 중인 광고비를 노출 순위별로 확인할 수 있는데요. 해당 데이터를 참고해 키워드 입찰 광고를 진행해 볼 수 있죠."
    },
    {
      "type": "image",
      "img_url": "https://core-cdn-fe.toss.im/image/optimize/?src=https://static.toss.im/ipd-tcs/toss_core/live/4ed42e94-132b-4fcb-ab33-8501a7c3281b/semo-85-inner-6-1536x864.jpg?&w=3840&q=75",
      "ocr_text": "키 워 드 로 보는 상 품 데 이 터 의 모 든 것\n\n종 합 분 석 연 관 키 워 5 판 매 가 능 상 품\n키 워 드 분 석\n여 성 양 말 ㅣ 현 재 스 토 어 1 위 상 품 진 단 하 기 엑 셀 다 운 로 드 _ 공 유 하 기\n“aes 63 1 위 카 테 고 리 패 션 잡 화 > 양 말 > 여 성 양 말 > 중 목 / 장 목 양 말 (1003)\n미 다수\nnal\n키 워 드 로 얻 는 모 든 정 보 oe\n키 워 드 분 석 사 용 방 범 > 큭 (nas\n\nzee adh. 국 산 여 성 무 지 골 .. ASHSMMS.. 、 여 자 양 말 패 션 무 지 …. _ 국 산 따 뜻 한 통 파 일 …. _ 양 말 모 음 전 국 산 …….\n40 원 960 원 0 원 1,590 원 2,250 원\n\n키 워 드 얼 마 나 검 색 하 지 ?\n\n윌 검 색 량 상 품 량 키 워 드 경 쟁 률 실 제 경 쟁 상 품 수\n19,870 회 4,515,461 개 227:1 6871"
    },
    {
      "type": "image",
      "img_url": "https://core-cdn-fe.toss.im/image/optimize/?src=https://static.toss.im/ipd-tcs/toss_core/live/45f2f744-d7b6-404b-91cb-c1d0f06f330d/semo-85-inner-7-1536x864.jpg?&w=3840&q=75",
      "ocr_text": "어 떤 상 품 을 팔 아 야 할 지 모 르 겠 다면\n\n키 워 드 찾 기\n\n쇼 핑 카 테 고 리\n검 색 어 로 찾 기 키 테 고 리 로 찾 기 패 션 잡 화 - 양 말 - 여 성 양 말 - 중 목 / 장 목 양 말\n-- 2023 년 018 02 일 00 시 기 준 | 카 테 고 리 BBS BAD (371791\n황 금 키 워 브 랜 드 추 가 _ 검 색 필 터 _ 숫 자 로 보 기 _ 엑 셀 다 운 로 드\n여 성 양 말 | 엔 터 ]\n키 워 드 경 쟁 률 ㅎ 쇼 핑 전 환 * 광 고 비 * 、 검 색 량 수 상 품 량 ㅎ _ 평 균 가 수\neS 폴 로 양 말 2 52 간 18,040 55,458 8,130\n키 워 드 찾 기 사 용 방 법 _ 〉 여 성 기 모 양 말 Lis 52 13,310 208,921 5,520\n캐 시 미 어 양 말 2 중 긴 : 11,470 29,410 3,410\n명 품 양 말 3 즉 us 8,280 41,395 9,370\n크 리 스 마 스 양 말 선 물 ue 초 중 7,210 118,946 3,900\n\n출 처 : 판 다 랭 크"
    },
    {
      "type": "text",
      "data": "사이트 내에 데이터가 이해하기 쉽게 정리되어 있어 키워드 분석이 처음인 사장님이 이용해 보기에 좋아요. 기본적인 키워드 분석 기능은 무료로 사용할 수 있어요."
    },
    {
      "type": "text",
      "data": "위 사이트들을 활용해 상품 키워드와 경쟁률을 비교해 보세요. 앞서 설명한 것처럼 경쟁률이 낮다고 무조건 좋은 것은 아니고, 경쟁률이 낮으면서도 검색 수가 너무 적지 않은 키워드를 찾는 것이 중요해요."
    },
    {
      "type": "image",
      "img_url": "https://core-cdn-fe.toss.im/image/optimize/?src=https://static.toss.im/ipd-tcs/toss_core/live/3dc9b06d-9c96-4201-98ca-9a80d906696e/semo-85-inner-8-1536x656.jpg?&w=3840&q=75",
      "ocr_text": "카 테 고 리\n\n230:1\n74:1\n\n4,503,765\n801,549\n6,577,959\n9,551,496\n\n19,590\n\n10,870\n9,690\n5,140\n\n13\n\n키 워 드\n\n72:1\n\n478,600\n\n6,680\n\n<|\n귀\n삐\n\nf\n\n페이"
    },
    {
      "type": "text",
      "data": "우선 해당 키워드를 상품명, 태그 등에 반영하고 키워드 광고에도 적용해 보세요. 이후 점차 수정해가며 광고 예산도 적절히 분배할 수 있어요. 효율이 좋은 키워드라면 광고 예산을 더 높여볼 수 있고요."
    },
    {
      "type": "text",
      "data": "이 방법을 사용하면 현재 사용 중인 키워드 효율도 체크할 수 있어요. 비효율적인 키워드를 활용하고 있었다면, 앞서 이야기한 서비스들을 통해 경쟁력이 뛰어난 키워드로 교체하며 판매량의 변화를 확인해 보세요."
    },
    {
      "type": "text",
      "data": "스마트스토어 키워드 최적화, 이렇게 시작하세요"
    },
    {
      "type": "text",
      "data": "상위노출을 위해서는 광고 외에 상품 등록에 있어서도 전략이 필요해요. 상품을 등록하는 과정부터 최적화가 잘 되어 있다면 많은 광고비를 들이지 않고도 노출 순위를 높여볼 수 있어요. 아래 내용을 바탕으로 기존 상품의 설정을 점검하고 신규 상품을 등록할 때에도 활용해 보세요."
    },
    {
      "type": "text",
      "data": "1️⃣ 상품명에 포함된 키워드 체크하기"
    },
    {
      "type": "text",
      "data": "효율이 뛰어난 키워드를 넣어 상품명을 작성하면 검색 노출 순위를 보다 높여볼 수 있는데요. 무조건 많은 키워드를 상품명에 넣는다고 순위가 올라가는 건 아니에요."
    },
    {
      "type": "text",
      "data": "일반적으로 상품 당 4~8개의 키워드를 넣는 게 좋아요. 강조하고 싶은 키워드는 앞쪽에 배치하면 되고요."
    },
    {
      "type": "text",
      "data": "상품명을 입력할 때 많은 사장님들이 노출 경쟁력을 고려해 복합 키워드를 많이 사용하는데요. 이때 단어 사이 띄어쓰기 여부를 주의해서 확인해야 해요. 키워드에 따라 띄어쓰기의 영향을 받는 경우도, 받지 않는 경우도 있기 때문이에요."
    },
    {
      "type": "text",
      "data": "예를 들어 네이버 쇼핑 탭에서 ‘생 삼겹살’과 ‘생삼겹살’을 검색하면 노출되는 상품이 다른데요. 이 경우 상품명에 ‘생 삼겹살’이라는 키워드를 사용했다면 ‘생삼겹살’로 검색했을 때 해당 상품이 보이지 않아요. 상품명 등록 전 미리 키워드를 검색해 보기를 추천드려요."
    },
    {
      "type": "image",
      "img_url": "https://core-cdn-fe.toss.im/image/optimize/?src=https://static.toss.im/ipd-tcs/toss_core/live/c1a15ba8-d8c2-4dbc-b5cb-8ae4612c2a63/semo-85-inner-9-1536x1118.jpg?&w=3840&q=75",
      "ocr_text": "ㆍ BAO 적 합 한 상 품 명 VHS 위 한 가 이 드 입 니 다 .\n\nㆍ 제 공 하 기 HAS 품 질 기 준 도 있 으 므 로 , AMS ASS 검 색 최 적 화 가 이 드 의 ' 상 품 명 ' 부 분 을 참 고 해 주 세\n요 .\n\nY\n\n검 색 품 질 체 크 항 목 에 맞 게 잘 입 력 되 었 습 니 다 .\n\n자 세 한 검 색 최 적 화 가 이 드 가 궁 금 하 다 면 ? 검 색 최 적 화 가 이드 확 인 >\n\n햅 Ｌ\n\n귀 여 운 여 성 봄 가 을 양 말 패 션 양 말 양 말 세 트 24/100\n\n판 매 상 품 과 직접 관 련이 없 는 다 른 SSS, 스 팸 성 키 워 드 입 력 시 권\n유 명 상 품 유 사 문 구 를 무 단 으 로 도 용 하 여 ~ 스 타 일 , ~st 등과 같 이 기 재 하 는\n\n전 용 상 품 명 을 사 용 중 인 경 우 대 표 상 품 명 수 정 시 에 도 전 용 상 품 명 으 로 노 출 됩 니\n상 품 명 을 검 색 최 적 화 가 이 드 에 잘 맞 게 입 력 하 면 검 색 노 줄 에 도 움 이 될 수 있 습 니 ㄷ ㅁ\n\n출 처 : 네 이버 스 마 트 스 토 어 센 터"
    },
    {
      "type": "text",
      "data": "추가로 상품명을 작성할 때는 중복 키워드가 포함되지는 않았는지 체크해 봐야 해요. 네이버 스마트스토어센터 [상품관리 > 상품 등록 > 상품명] 하단"
    },
    {
      "type": "text",
      "data": "‘상품명 검색품질 체크’에서 중복 키워드 포함 여부를 점검할 수 있어요."
    },
    {
      "type": "text",
      "data": "2️⃣ 키워드 상단 노출 상품과 카테고리 일치 여부 확인하기"
    },
    {
      "type": "image",
      "img_url": "https://core-cdn-fe.toss.im/image/optimize/?src=https://static.toss.im/ipd-tcs/toss_core/live/fb676f46-b103-4427-b7e3-9c9ac459263a/semo-85-inner-10-1536x469.jpg?&w=3840&q=75",
      "ocr_text": "@'e\na\nae\n% Ve\n*\n\n귀 여 운 여 성 봄 가 을 양 말 패 션 양 말 양 말 세 트\n700 원 = 3.000 원\n\n때 션 잡 화 > 양 말 > 여 성 양 말 > 중 목 / 장 목 양 말\n사 용 계 절 : 봄 , 여 름 , 가 음 , As 성 별 : 여 성 용\n\n2] 112,506 ㆍ 구 매 건 수 82,923 ㆍ 등 록 일 2021.03.\n\n<2 찜 하 기 15722 ㆍ 의 신 고 하 기\n\n므"
    },
    {
      "type": "text",
      "data": "상위노출을 노린다면 상품 등록 ‘카테고리’까지 꼼꼼히 확인해두는 게 좋은데요."
    },
    {
      "type": "text",
      "data": "키워드를 검색했을 때 제일 먼저 노출되는 상품과 동일한 카테고리로 설정하면 돼요."
    },
    {
      "type": "text",
      "data": "만약 기존에 등록한 상품 중 최상단 노출 상품과 다른 카테고리로 설정된 것이 있다면 수정해 주세요."
    },
    {
      "type": "text",
      "data": "3️⃣ 상품 등록 페이지 내 상세 설정 점검하기"
    },
    {
      "type": "text",
      "data": "스마트스토어 상품 등록 과정에서 기본 정보 외에도 태그나 상품 속성 등을 함께 작성하게 되는데요. 모든 내용이 빠짐없이 잘 입력되었는지 꼭 체크해야 해요."
    },
    {
      "type": "text",
      "data": "상품 태그를 입력할 때에는 ‘양말(1234)’와 같이 괄호 안에 태그 아이디가 존재하는 상태로 등록되었는지 확인해 주세요. 추가로 상품 종류에 따라 입력을 권장하는 상품 속성이 달라지는데요. 가능하다면 모든 항목에 대해 속성을 설정해두는 게 좋아요."
    },
    {
      "type": "image",
      "img_url": "https://core-cdn-fe.toss.im/image/optimize/?src=https://static.toss.im/ipd-tcs/toss_core/live/2dca4e7f-a8be-414b-a541-8837712f3577/semo-85-inner-11-1536x1055.jpg?&w=3840&q=75",
      "ocr_text": "상 품 정 보 검 색 품 질 체 크\n\nㆍ 검 색 인 기 도와 관 련 있 는 주 요 항 목 들 을 가 이 드 에 맞 게 잘 입 력 하 면 검 색 노 출 기 회 가 늘 어 납 니 다 .\nㆍ 점 검 필 요 에 빨 간 붙 이 SoS HSS 입 력 한 내 용 을 한 번 더 확 인 해 주 세 요 .\n\nas 확 인 점 검 필 요\n상 품 명 _ 체 크 항 목 0건 으\n카 테 고 리 . 패 션 잡 화 > 양 말 > 여 성 양 말 > 중 목 / 장 목 양 말 :\n브 랜 드 _ 입 력 안 됨 @\n제 조 사 _ 스 튜 디 오 베 케 이 션 \"\n속 성 _ , 입 력 5 건 〉\n태 그 _ 、 입 력 4건 / 검 색 적 용 4건 -\n\n자 세 한 검 색 최 적 화 가 이 드 가 궁 금 하 다 면 ? 검 색 최 적 화 가 이드 확 인 >\n\n출 처 : 네 이버 스 마 트 스 토 어 센 터"
    },
    {
      "type": "text",
      "data": "마지막으로 상품 등록 페이지 하단의 ‘상품정보 검색품질 체크‘ 버튼을 눌러 필요한 내용이 모두 입력되어 있는지 확인해 주세요. 빨간불이 들어온 항목이 있다면 다시 수정해야 해요."
    },
    {
      "type": "text",
      "data": "가이드에 따라 필요한 내용이 잘 입력되어 있을수록 상품이 상위에 노출될 가능성이 높아져요."
    },
    {
      "type": "text",
      "data": "💪"
    },
    {
      "type": "text",
      "data": "바쁜 사장님을 위한 3줄 정리"
    },
    {
      "type": "text",
      "data": "스마트스토어 상품명과 태그, 광고 등에 키워드를 활용하면 상품의 검색 노출 순위를 높일 수 있어요."
    },
    {
      "type": "text",
      "data": "키워드 효율을 분석할 때는 검색량, 관련 상품 수, 검색 시 최상단에 쇼핑 영역이 노출되는지를 고려해 봐야 해요."
    },
    {
      "type": "text",
      "data": "검색 상위 노출을 위해서는 상품 등록 시 상세 설정 내용을 꼼꼼히 점검해야 해요."
    },
    {
      "type": "text",
      "data": "📍 함께 읽으면 좋을 콘텐츠"
    },
    {
      "type": "text",
      "data": "사업의 성장을 돕는 그로스 파트너 토스페이먼츠"
    },
    {
      "type": "text",
      "data": "토스페이먼츠는 대한민국 전자결제 시장을 새롭게 바꿔나가는 것을 목표로 합니다.\n쉽고 빠른 PG 연동은 물론, 결제전환율을 높이고 브랜딩까지 해주는 서비스로 확장하고 있습니다."
    },
    {
      "type": "text",
      "data": "결제가 불편한 모든 순간 토스페이먼츠의 문을 두드려주세요."
    },
    {
      "type": "image",
      "img_url": "https://core-cdn-fe.toss.im/image/optimize/?src=https://static.toss.im/ipd-tcs/toss_core/live/c0614cfa-9eaa-4d4d-957c-ed38051d0d12/CTA-범용-왼1.jpg?&w=3840&q=75",
      "ocr_text": "@® toss payments\n성 공 적 인 비 즈 니 스 ,\n토 스 페 이 먼 츠 와 함 께 하 세 요"
    },
    {
      "type": "text",
      "data": "Edit"
    },
    {
      "type": "text",
      "data": "유서진, 고예일"
    },
    {
      "type": "text",
      "data": "Graphic"
    },
    {
      "type": "text",
      "data": "이은호, 이나눔"
    },
    {
      "type": "text",
      "data": "토스페이먼츠의 모든 콘텐츠는 사업자에게 도움이 될 만한 일반적인 정보를 ‘참고 목적’으로 한정해 제공하고 있습니다. 구체적 사안에 관한 자문 또는 홍보를 위한 것이 아니므로 콘텐츠 내용의 적법성이나 정확성에 대해 보증하지 않으며, 콘텐츠에서 취득한 정보로 인해 직간접적인 손해가 발생해도 어떠한 법적 책임도 부담하지 않습니다."
    },
    {
      "type": "text",
      "data": "ⓒ토스페이먼츠, 무단 전재 및 배포 금지"
    },
    {
      "type": "text",
      "data": "토스페이먼츠 서비스 소개서"
    },
    {
      "type": "image",
      "img_url": "https://core-cdn-fe.toss.im/image/optimize/?src=https://blog-cdn.tosspayments.com/wp-content/uploads/2022/09/06211020/payments.png?&w=3840&q=75",
      "ocr_text": ""
    },
    {
      "type": "text",
      "data": "토스페이먼츠"
    },
    {
      "type": "text",
      "data": "고객사의 성장이 곧 우리의 성장이라는 확신을 가지고 더 나은 결제 경험을 만듭니다. 결제가 불편한 순간을 기록하고 바꿔갈게요."
    }
  ]
}